pyudx/__init__.py
pyudx/address.py
pyudx/asset.py
pyudx/crypto.py
pyudx/order.py
PyUDX-0.0.5.dist-info/LICENSE
PyUDX-0.0.5.dist-info/METADATA
PyUDX-0.0.5.dist-info/WHEEL
PyUDX-0.0.5.dist-info/top_level.txt
PyUDX-0.0.5.dist-info/RECORD
